{
  "openapi": "3.0.4",
  "info": {
    "title": "WeatherApp.API",
    "version": "1.0"
  },
  "paths": {
    "/api/Auth/login": {
      "post": {
        "tags": [
          "Auth"
        ],
        "requestBody": {
          "content": {
            "application/json": {
              "schema": {
                "$ref": "#/components/schemas/LoginRequest"
              }
            },
            "text/json": {
              "schema": {
                "$ref": "#/components/schemas/LoginRequest"
              }
            },
            "application/*+json": {
              "schema": {
                "$ref": "#/components/schemas/LoginRequest"
              }
            }
          }
        },
        "responses": {
          "200": {
            "description": "OK"
          }
        }
      }
    },
    "/api/Weather/save": {
      "post": {
        "tags": [
          "Weather"
        ],
        "requestBody": {
          "content": {
            "application/json": {
              "schema": {
                "$ref": "#/components/schemas/SaveWeatherRequest"
              }
            },
            "text/json": {
              "schema": {
                "$ref": "#/components/schemas/SaveWeatherRequest"
              }
            },
            "application/*+json": {
              "schema": {
                "$ref": "#/components/schemas/SaveWeatherRequest"
              }
            }
          }
        },
        "responses": {
          "200": {
            "description": "OK"
          }
        }
      }
    },
    "/api/Weather/searches": {
      "get": {
        "tags": [
          "Weather"
        ],
        "parameters": [
          {
            "name": "cityName",
            "in": "query",
            "schema": {
              "type": "string"
            }
          },
          {
            "name": "userId",
            "in": "query",
            "schema": {
              "type": "integer",
              "format": "int32"
            }
          }
        ],
        "responses": {
          "200": {
            "description": "OK"
          }
        }
      }
    },
    "/api/Weather/update": {
      "put": {
        "tags": [
          "Weather"
        ],
        "requestBody": {
          "content": {
            "application/json": {
              "schema": {
                "$ref": "#/components/schemas/UpdateWeatherRequest"
              }
            },
            "text/json": {
              "schema": {
                "$ref": "#/components/schemas/UpdateWeatherRequest"
              }
            },
            "application/*+json": {
              "schema": {
                "$ref": "#/components/schemas/UpdateWeatherRequest"
              }
            }
          }
        },
        "responses": {
          "200": {
            "description": "OK"
          }
        }
      }
    },
    "/WeatherForecast": {
      "get": {
        "tags": [
          "WeatherForecast"
        ],
        "operationId": "GetWeatherForecast",
        "responses": {
          "200": {
            "description": "OK",
            "content": {
              "text/plain": {
                "schema": {
                  "type": "array",
                  "items": {
                    "$ref": "#/components/schemas/WeatherForecast"
                  }
                }
              },
              "application/json": {
                "schema": {
                  "type": "array",
                  "items": {
                    "$ref": "#/components/schemas/WeatherForecast"
                  }
                }
              },
              "text/json": {
                "schema": {
                  "type": "array",
                  "items": {
                    "$ref": "#/components/schemas/WeatherForecast"
                  }
                }
              }
            }
          }
        }
      }
    }
  },
  "components": {
    "schemas": {
      "LoginRequest": {
        "type": "object",
        "properties": {
          "username": {
            "type": "string",
            "nullable": true
          },
          "password": {
            "type": "string",
            "nullable": true
          }
        },
        "additionalProperties": false
      },
      "SaveWeatherRequest": {
        "type": "object",
        "properties": {
          "userId": {
            "type": "integer",
            "format": "int32"
          },
          "cityName": {
            "type": "string",
            "nullable": true
          },
          "countryCode": {
            "type": "string",
            "nullable": true
          },
          "humidity": {
            "type": "integer",
            "format": "int32"
          },
          "tempMin": {
            "type": "number",
            "format": "double"
          },
          "tempMax": {
            "type": "number",
            "format": "double"
          }
        },
        "additionalProperties": false
      },
      "UpdateWeatherRequest": {
        "type": "object",
        "properties": {
          "searchId": {
            "type": "integer",
            "format": "int32"
          },
          "cityName": {
            "type": "string",
            "nullable": true
          },
          "humidity": {
            "type": "integer",
            "format": "int32"
          },
          "tempMin": {
            "type": "number",
            "format": "double"
          },
          "tempMax": {
            "type": "number",
            "format": "double"
          },
          "changedByUserId": {
            "type": "integer",
            "format": "int32"
          }
        },
        "additionalProperties": false
      },
      "WeatherForecast": {
        "type": "object",
        "properties": {
          "date": {
            "type": "string",
            "format": "date"
          },
          "temperatureC": {
            "type": "integer",
            "format": "int32"
          },
          "temperatureF": {
            "type": "integer",
            "format": "int32",
            "readOnly": true
          },
          "summary": {
            "type": "string",
            "nullable": true
          }
        },
        "additionalProperties": false
      }
    }
  },
  "tags": [
    {
      "name": "Auth"
    },
    {
      "name": "Weather"
    },
    {
      "name": "WeatherForecast"
    }
  ]
}